libHalf.so.23
libblosc.so.1
libboost_iostreams.so.1.68.0
libboost_numpy37.so.1.68.0
libboost_python37.so.1.68.0
liblog4cplus-1.1.so.9
libm.so.6
libopenvdb.so.7.1
libsnappy.so.1
libtbb.so.2
libtbbmalloc.so.2
libtbbmalloc_proxy.so.2
libzstd.so.1.3.8
pyopenvdb.so
openvdb/__init__.py
pyopenvdb-0.1.4.dist-info/LICENSE
pyopenvdb-0.1.4.dist-info/METADATA
pyopenvdb-0.1.4.dist-info/WHEEL
pyopenvdb-0.1.4.dist-info/top_level.txt
pyopenvdb-0.1.4.dist-info/RECORD
