Metadata-Version: 2.1
Name: pyopenvdb
Version: 0.1.4
Summary: Python bindings for Open Voxel Database
Home-page: https://github.com/theNewFlesh/docker_pyopenvdb
Author: Alex Braun
Author-email: Alexander.G.Braun@gmail.com
License: MPL version 2.0
Download-URL: https://github.com/theNewFlesh/docker_pyopenvdb/archive/0.1.4.tar.gz
Keywords: OpenVDB,pyopenvdb
Platform: UNKNOWN
Classifier: Development Status :: 4 - Beta
Classifier: Intended Audience :: Developers
Classifier: Programming Language :: Python :: 3
Classifier: Programming Language :: Python :: 3.7
Requires-Dist: numpy (>=1.16.2)
